pyperp/abi/arbitrumRinkeby/AccountBalance.json
pyperp/abi/arbitrumRinkeby/BTCUSDChainlinkPriceFeed.json
pyperp/abi/arbitrumRinkeby/ClearingHouse.json
pyperp/abi/arbitrumRinkeby/ClearingHouseConfig.json
pyperp/abi/arbitrumRinkeby/ETHUSDChainlinkPriceFeed.json
pyperp/abi/arbitrumRinkeby/Exchange.json
pyperp/abi/arbitrumRinkeby/InsuranceFund.json
pyperp/abi/arbitrumRinkeby/MarketRegistry.json
pyperp/abi/arbitrumRinkeby/OrderBook.json
pyperp/abi/arbitrumRinkeby/QuoteToken.json
pyperp/abi/arbitrumRinkeby/USDC.json
pyperp/abi/arbitrumRinkeby/UniswapV3Factory.json
pyperp/abi/arbitrumRinkeby/Vault.json
pyperp/abi/arbitrumRinkeby/vBTC.json
pyperp/abi/arbitrumRinkeby/vBTCvUSDUniswapV3Pool.json
pyperp/abi/arbitrumRinkeby/vETH.json
pyperp/abi/arbitrumRinkeby/vETHvUSDUniswapV3Pool.json
pyperp/abi/optimism/AccountBalance.json
pyperp/abi/optimism/BTCUSDChainlinkPriceFeed.json
pyperp/abi/optimism/ClearingHouse.json
pyperp/abi/optimism/ClearingHouseConfig.json
pyperp/abi/optimism/ETHUSDChainlinkPriceFeed.json
pyperp/abi/optimism/Exchange.json
pyperp/abi/optimism/InsuranceFund.json
pyperp/abi/optimism/MarketRegistry.json
pyperp/abi/optimism/OrderBook.json
pyperp/abi/optimism/QuoteToken.json
pyperp/abi/optimism/USDC.json
pyperp/abi/optimism/UniswapV3Factory.json
pyperp/abi/optimism/Vault.json
pyperp/abi/optimism/vBTC.json
pyperp/abi/optimism/vBTCvUSDUniswapV3Pool.json
pyperp/abi/optimism/vETH.json
pyperp/abi/optimism/vETHvUSDUniswapV3Pool.json
pyperp/abi/optimismKovan/AccountBalance.json
pyperp/abi/optimismKovan/BTCUSDChainlinkPriceFeed.json
pyperp/abi/optimismKovan/ClearingHouse.json
pyperp/abi/optimismKovan/ClearingHouseConfig.json
pyperp/abi/optimismKovan/ETHUSDChainlinkPriceFeed.json
pyperp/abi/optimismKovan/Exchange.json
pyperp/abi/optimismKovan/InsuranceFund.json
pyperp/abi/optimismKovan/MarketRegistry.json
pyperp/abi/optimismKovan/OrderBook.json
pyperp/abi/optimismKovan/QuoteToken.json
pyperp/abi/optimismKovan/USDC.json
pyperp/abi/optimismKovan/UniswapV3Factory.json
pyperp-2.0.0.dist-info/LICENSE
pyperp-2.0.0.dist-info/METADATA
pyperp-2.0.0.dist-info/WHEEL
pyperp-2.0.0.dist-info/top_level.txt
pyperp-2.0.0.dist-info/RECORD
