Metadata-Version: 2.1
Name: pyperp
Version: 2.0.0
Summary: python SDK for Perpetual Protocol
Home-page: https://github.com/DeveloperInProgress/PyPerp
Author: Naveen Veluswamy
Author-email: velnaveen99@gmail.com
License: MIT
Keywords: perp,perpetual protocol,defi
Platform: UNKNOWN
Classifier: Development Status :: 5 - Production/Stable
Classifier: Intended Audience :: Developers
Classifier: Topic :: Software Development :: Build Tools
Classifier: License :: OSI Approved :: MIT License
Classifier: Programming Language :: Python :: 3.6
Classifier: Programming Language :: Python :: 3.7
Classifier: Programming Language :: Python :: 3.8
Classifier: Programming Language :: Python :: 3.9
License-File: LICENSE
Requires-Dist: web3 (>=5.24.0)
Requires-Dist: datetime (>=4.3)
